setup.cfg
setup.py
tarindex/__init__.py
tarindex.egg-info/PKG-INFO
tarindex.egg-info/SOURCES.txt
tarindex.egg-info/dependency_links.txt
tarindex.egg-info/top_level.txt